{
  "templateId":"handnote-33","styleFamily":"handnote","name":"淡紫纸+深紫字+星星涂鸦+星空笔记",
  "canvas":[1242,1656],
  "background":{"type":"solid","color":"#FAF8FD","overlay":{"type":"dots","spacing":22,"color":"rgba(120,80,180,0.06)","dotSize":2}},
  "titleBox":{"x":100,"y":440,"w":1042,"h":520},
  "titleFont":{"family":"\"Noto Sans SC\",sans-serif","min":150,"max":290,"weight":900,"color":"#4A2080","letterSpacing":-0.03},
  "subTitleBox":{"x":160,"y":1000,"w":920,"h":80},
  "subTitleFont":{"family":"\"Noto Sans SC\",sans-serif","min":40,"max":76,"weight":400,"color":"rgba(74,32,128,0.50)"},
  "decorations":[
    {"id":"hn33-tape","type":"tape","layer":"above","box":{"x":430,"y":235,"w":290,"h":34},"rotation":-4,"color":"rgba(170,140,210,0.45)"},
    {"id":"hn33-highlighter","type":"highlighter","layer":"behind","box":{"x":140,"y":710,"w":960,"h":46},"color":"rgba(180,150,230,0.28)"},
    {"id":"hn33-stamp","type":"stamp","layer":"above","box":{"x":1000,"y":150,"w":115,"h":115},"color":"#6B3FA0","rotation":-8,"label":"STAR"},
    {"id":"hn33-emoji","type":"emoji","layer":"above","box":{"x":95,"y":1380,"w":110,"h":110},"emoji":"🌙","fontSize":100}
  ]
}
